{"changelog.md":"DxcI6ECB","contributing.md":"DjP8OZ4N","examples.md":"CX_kvKzO","examples_crud-basic.md":"Bz6cDehi","examples_crud-inline.md":"BTz38tLY","examples_crud-nested.md":"C6TfjnIH","examples_default.md":"BRBElDOt","examples_file-handling.md":"ChRkK15v","examples_react-fetch.md":"B6h74hgM","examples_with-auth.md":"Cyoj52Dp","features_background-jobs.md":"DI86jjtE","features_cli.md":"DhdQxCE3","features_config-files.md":"-vzl1t2I","features_extending-the-cli.md":"C07Yt_Ee","features_file-handling.md":"BJ8CnWhL","features_getting-started.md":"E-IBGthA","features_http-server.md":"CMzQVe0z","features_logger-and-events.md":"BPw7kMFw","features_migrations.md":"GP6ayrl-","features_postgres-and-s3.md":"MSgxNMQg","features_session-handling.md":"BkTqfrLh","features_test-and-bench-runner.md":"qo0EG7Lu","features_typescript-setup.md":"BGGGaOna","generators_build-structure_crud.md":"BgEoTR-a","generators_build-structure_entities.md":"0oMoK9Rp","generators_build-structure_routes.md":"BXlnqZku","generators_build-structure_types-and-validators.md":"CKcyVXjN","generators_importing-structure.md":"CKJdbLxo","generators_introduction.md":"BZdl1ODj","generators_targets.md":"CiinXiss","generators_usage_axios-api-client.md":"Dm9UmuJ5","generators_usage_js-postgres.md":"CSBeK4XR","generators_usage_koa-router.md":"CN-0wa4j","index.md":"WzVU6Bhf","references_cli.md":"DhPVInyO","references_compas-config.md":"C6421cHu","references_store.md":"B_EoKdAD","releases_code-gen-migration.md":"44IwSgyt","releases_index.md":"CiZJRtCn"}
